identity_sdk/__init__.py
identity_sdk-0.1.0.dist-info/WHEEL
identity_sdk-0.1.0.dist-info/METADATA
identity_sdk-0.1.0.dist-info/RECORD
